MANIFEST.in
README.md
setup.py
django_readonly_site.egg-info/PKG-INFO
django_readonly_site.egg-info/SOURCES.txt
django_readonly_site.egg-info/dependency_links.txt
django_readonly_site.egg-info/not-zip-safe
django_readonly_site.egg-info/requires.txt
django_readonly_site.egg-info/top_level.txt
readonly/__init__.py
readonly/middleware.py
readonly/templates/readonly/readonly.html