Metadata-Version: 1.1
Name: django-readonly-site
Version: 0.1.2
Summary: Middleware to take your Django website offline by changing settings.SITE_READ_ONLY
Home-page: http://github.com/rossp/django-readonly-site
Author: Ross Poulton
Author-email: ross@rossp.org
License: BSD
Keywords: django
Platform: UNKNOWN
Classifier: Programming Language :: Python
Classifier: Topic :: Software Development :: Libraries :: Python Modules
Classifier: Framework :: Django
Classifier: Environment :: Web Environment
Classifier: Operating System :: OS Independent
Classifier: License :: OSI Approved :: BSD License
Classifier: Natural Language :: English
Classifier: Intended Audience :: Developers
Classifier: Development Status :: 3 - Alpha
